{
  "schema_version": 1,
  "event_id": "acfbfc21-866e-4157-add9-39fbc9f7a0f0",
  "issue_id": "plx-c1d62f75-5ee5-4d95-b9cd-b5a7b13d2923",
  "event_type": "issue_created",
  "occurred_at": "2026-04-02T13:21:09.861Z",
  "actor_id": "ryan",
  "payload": {
    "assignee": null,
    "description": "## Summary\nReuse the dashboard's existing warning/alert presentation patterns for evaluation-level misclassification red flags.\n\n## Deliverables\n- Surface evaluation-level flags using an established warning/error visual treatment.\n- Keep the visual treatment coherent with existing dashboard report and evaluation warning patterns.\n- Define how multiple flags are summarized without overwhelming the evaluation view.",
    "issue_type": "task",
    "labels": [],
    "parent": "plx-f78d0806-4821-434f-a96d-6d64bb30b645",
    "priority": 2,
    "status": "open",
    "title": "Reuse dashboard warning/alert components for evaluation-level red flags"
  }
}